streetviewdownloader/__init__.py
streetviewdownloader/__main__.py
streetviewdownloader/basepbfsource.py
streetviewdownloader/basestreetviewdownloaderthread.py
streetviewdownloader/basestreetviewsource.py
streetviewdownloader/bbbikesource.py
streetviewdownloader/cache.py
streetviewdownloader/cachingrequestssession.py
streetviewdownloader/extractfinder.py
streetviewdownloader/geofabriksource.py
streetviewdownloader/pbffilereader.py
streetviewdownloader/split_list.py
streetviewdownloader/streetnetworkdownloader.py
streetviewdownloader/streetnetworkpointgenerator.py
streetviewdownloader/streetviewdownloader.py
streetviewdownloader/streetviewimagedownloader.py
streetviewdownloader/streetviewimagedownloaderthread.py
streetviewdownloader/streetviewimagesource.py
streetviewdownloader/streetviewmetadatadownloader.py
streetviewdownloader/streetviewmetadatadownloaderthread.py
streetviewdownloader/streetviewmetadatasource.py
streetviewdownloader/streetviewstaticapiauth.py
streetviewdownloader-0.2.6.dist-info/METADATA
streetviewdownloader-0.2.6.dist-info/WHEEL
streetviewdownloader-0.2.6.dist-info/top_level.txt
streetviewdownloader-0.2.6.dist-info/RECORD
