Metadata-Version: 2.1
Name: streetviewdownloader
Version: 0.2.6
Summary: A Python library and utility to download Google StreetView images
Author-email: Christoph Fink <christoph.fink@helsinki.fi>
License: GPL-3.0-or-later
Project-URL: Documentation, https://streetviewdownloader.readthedocs.io/
Project-URL: Repository, https://github.com/DigitalGeographyLab/streetviewdownloader/
Project-URL: Change log, https://github.com/DigitalGeographyLab/streetviewdownloader/blob/main/CHANGELOG.md
Project-URL: Bug tracker, https://github.com/DigitalGeographyLab/streetviewdownloader/issues
Classifier: Programming Language :: Python :: 3
Classifier: License :: OSI Approved :: GNU General Public License v3 (GPLv3)
Classifier: Operating System :: OS Independent
Requires-Python: >=3.9
Requires-Dist: ConfigArgParse
Requires-Dist: geopandas
Requires-Dist: numpy
Requires-Dist: pandas
Requires-Dist: pygeos
Requires-Dist: pyproj
Requires-Dist: pyrosm
Requires-Dist: pyxdg
Requires-Dist: requests
Requires-Dist: shapely
Provides-Extra: docs
Requires-Dist: contextily ; extra == 'docs'
Requires-Dist: ipycache ; extra == 'docs'
Requires-Dist: ipykernel ; extra == 'docs'
Requires-Dist: ipyleaflet ; extra == 'docs'
Requires-Dist: ipython ; extra == 'docs'
Requires-Dist: ipython-genutils ; extra == 'docs'
Requires-Dist: ipywidgets ; extra == 'docs'
Requires-Dist: nbsphinx ; extra == 'docs'
Requires-Dist: Sphinx ; extra == 'docs'
Requires-Dist: sphinx-rtd-theme ; extra == 'docs'
Requires-Dist: sphinxcontrib-applehelp ; extra == 'docs'
Requires-Dist: sphinxcontrib-devhelp ; extra == 'docs'
Requires-Dist: sphinxcontrib-htmlhelp ; extra == 'docs'
Requires-Dist: sphinxcontrib-jsmath ; extra == 'docs'
Requires-Dist: sphinxcontrib-qthelp ; extra == 'docs'
Requires-Dist: sphinxcontrib-serializinghtml ; extra == 'docs'
